ahp_graph/Device.py
ahp_graph/DeviceGraph.py
ahp_graph/SSTGraph.py
ahp_graph/__init__.py
ahp_graph/py.typed
ahp_graph-2.0.4.dist-info/METADATA
ahp_graph-2.0.4.dist-info/WHEEL
ahp_graph-2.0.4.dist-info/licenses/LICENSE
ahp_graph-2.0.4.dist-info/RECORD
