Metadata-Version: 2.1
Name: ahp_graph
Version: 2.0.4
Summary: Attributed Hierarchical Port Graph
Project-URL: Homepage, https://github.com/lpsmodsim/ahp_graph
Author-email: lpsmodsim <modsim@lps.umd.edu>
License: Permission is hereby granted, free of charge, to any person obtaining a copy of this software and associated documentation files (the "Software"), to deal in the Software without restriction, including without limitation the rights to use, copy, modify, merge, publish, distribute, sublicense, and/or sell copies of the Software, and to permit persons to whom the Software is furnished to do so, subject to the following conditions:
License-File: LICENSE
Classifier: License :: OSI Approved :: MIT License
Classifier: Operating System :: OS Independent
Classifier: Programming Language :: Python :: 3
Requires-Python: >=3.9
Requires-Dist: orjson
Requires-Dist: pygraphviz
